bps_oculus/__init__.py
bps_oculus/_version.py
bps_oculus/core.py
bps_oculus/helpers.py
bps_oculus/io.py
bps_oculus/oculus.py
bps_oculus/logger/__init__.py
bps_oculus/logger/v1.py
bps_oculus/logger/v2.py
oculus_python-0.0.2a1.dist-info/licenses/LICENSE
oculus_python-0.0.2a1.dist-info/METADATA
oculus_python-0.0.2a1.dist-info/WHEEL
oculus_python-0.0.2a1.dist-info/entry_points.txt
oculus_python-0.0.2a1.dist-info/top_level.txt
oculus_python-0.0.2a1.dist-info/RECORD
