Metadata-Version: 2.4
Name: oculus-python
Version: 0.0.2a1
Summary: A python library for importing and exporting Blueprint Subsea Oculus imaging sonar log files.
Author-email: Fletcher Thompson <fletho@aqua.dtu.dk>
Project-URL: Homepage, https://gitlab.gbar.dtu.dk/fletho/oculus-python
Project-URL: Issues, https://gitlab.gbar.dtu.dk/fletho/oculus-python/-/issues
Classifier: Programming Language :: Python :: 3
Classifier: License :: OSI Approved :: Apache Software License
Classifier: Operating System :: OS Independent
Requires-Python: >=3.10
License-File: LICENSE
Requires-Dist: netCDF4
Requires-Dist: xarray
Requires-Dist: dask
Requires-Dist: opencv-python
Requires-Dist: rosbags
Dynamic: license-file
